{"description": "\u307e\u304b jonas - one direction", "text": "RT @AshBenzo: Are you Gaga, Beyonce, Britney, Katy, or Taylor? https://t.co/o9o0NakPcz", "hashtags": [], "user_location": null, "user_mentions": [{"indices": [3, 12], "screen_name": "AshBenzo", "id": 33597201, "name": "Ashley Benson", "id_str": "33597201"}], "followers": 1405, "timestamp": "1485421230665", "following": 1980, "in_reply_to_screen_name": null, "screen_name": "TellMeLiess"}
{"description": "NOT a 'do nothing' bitch || #BeyHive #ShawnMendes #TheWalkingDead {} sleepy Shawn is the best Shawn", "text": "RT @_BluRay__: I think about this often. There's no way Beyonc\u00e9 can stop dropping visual albums. The mystery is how she's gonna ev\u2026 ", "hashtags": [], "user_location": "beehive", "user_mentions": [{"indices": [3, 13], "screen_name": "_BluRay__", "id": 2599258549, "name": "Ray", "id_str": "2599258549"}], "followers": 7184, "timestamp": "1485421769659", "following": 6462, "in_reply_to_screen_name": null, "screen_name": "_liyss"}
{"description": "Now if you\u2019ll excuse me, I\u2019ve gotta go kill myself. Or max out my credit card; whichever comes first.", "text": "RT @beyupdates_: Wikihow turned Obama, Beyonc\u00e9, and Jay Z white to explain \"How to become a congressman.\" https://t.co/QNTGz5wjaq", "hashtags": [], "user_location": "Camp Nou", "user_mentions": [{"indices": [3, 15], "screen_name": "beyupdates_", "id": 2790516742, "name": "FORMATION", "id_str": "2790516742"}], "followers": 2586, "timestamp": "1485421792659", "following": 1074, "in_reply_to_screen_name": null, "screen_name": "siagalal"}
{"description": null, "text": "I've liked Beyonc\u00e9 since I was 6 ACTUALLY https://t.co/pkpea3fxc0", "hashtags": [], "user_location": "Unknown ", "user_mentions": [], "followers": 1945, "timestamp": "1485421951664", "following": 508, "in_reply_to_screen_name": null, "screen_name": "tyronedover4"}
{"description": "\ud83d\udcdd Journalist \n\ud83d\udc4d Social Media Analyst \n\ud83d\udcac Comic Book enthusiast", "text": "RT @ComicBookNOW: ICYMI: MARVEL Artist Shares BEYONCE Inspired Comic Book Cover\nhttps://t.co/2wyXRbPCvE https://t.co/XqVTMf9yAp", "hashtags": [], "user_location": "Sorocaba,SP - Brasil ", "user_mentions": [{"indices": [3, 16], "screen_name": "ComicBookNOW", "id": 2896294831, "name": "ComicBook NOW!", "id_str": "2896294831"}], "followers": 240, "timestamp": "1485422068657", "following": 483, "in_reply_to_screen_name": null, "screen_name": "binhodevito"}
{"description": null, "text": "#Now2016 #NOWFifthHarmony #VideoMTV2016 Fifth Harmony Beyonc\u00e9 https://t.co/gHLxbzaLXG https://t.co/G8LnGeqDEv", "hashtags": [{"indices": [0, 8], "text": "Now2016"}, {"indices": [9, 25], "text": "NOWFifthHarmony"}, {"indices": [26, 39], "text": "VideoMTV2016"}], "user_location": "Miami, FL", "user_mentions": [], "followers": 62, "timestamp": "1485422415663", "following": 44, "in_reply_to_screen_name": null, "screen_name": "lmjbissexuall"}
{"description": null, "text": "#NOW2016 #NOWFifthHarmony #VideoMTV2016 Fifth Harmony / Beyonc\u00e9 https://t.co/bNb4zp8qB3 https://t.co/y2BiO9nHID", "hashtags": [{"indices": [0, 8], "text": "NOW2016"}, {"indices": [9, 25], "text": "NOWFifthHarmony"}, {"indices": [26, 39], "text": "VideoMTV2016"}], "user_location": null, "user_mentions": [], "followers": 0, "timestamp": "1485422534664", "following": 0, "in_reply_to_screen_name": null, "screen_name": "attack5h4rmony4"}
{"description": "But hard work will not let you down. If you want to become stronger you have to practice a lot and aim to be number one.", "text": "*Toby called out and as the leader boy accidentally threw his bey at @TheRotationKing's face again by noticing some strange cute", "hashtags": [], "user_location": "Team Dungeon", "user_mentions": [{"indices": [69, 85], "screen_name": "TheRotationKing", "id": 2800968340, "name": "King \u2014 \u30ad\u30f3\u30b0.", "id_str": "2800968340"}], "followers": 8, "timestamp": "1485422715663", "following": 34, "in_reply_to_screen_name": null, "screen_name": "SpiralOfLyre"}
{"description": "I'm always there for girls to give them advice and when I try to talk to them all I get is the cold shoulder.", "text": "Who Are Beyonce's Super Bowl Backup Dancers? Her Instagram Video Previews #Instagram https://t.co/zU1gpiPsgQ #instagram", "hashtags": [{"indices": [74, 84], "text": "Instagram"}, {"indices": [109, 119], "text": "instagram"}], "user_location": "Idaho", "user_mentions": [], "followers": 20450, "timestamp": "1485423020661", "following": 22692, "in_reply_to_screen_name": null, "screen_name": "tanyaqiin"}
{"description": "from @lmjcrown", "text": "#VideoMTV2016 Fifth Harmony and Beyonc\u00e9 #NOW2016 #NOWFifthHarmony https://t.co/thhqwzuKB4", "hashtags": [{"indices": [0, 13], "text": "VideoMTV2016"}, {"indices": [40, 48], "text": "NOW2016"}, {"indices": [49, 65], "text": "NOWFifthHarmony"}], "user_location": null, "user_mentions": [], "followers": 0, "timestamp": "1485423023658", "following": 1, "in_reply_to_screen_name": null, "screen_name": "DrunkForDinahJ"}
{"description": "Proud Momma \ud83d\udc9c", "text": "RT @TheJakolDiaries: HEY, BEYONCE, RIHANNA AND NICKI? WHO DO YOU THINK WILL SLAY THE UNIVERSE THIS JANUARY 30TH? #MissUniverse\u2026 ", "hashtags": [{"indices": [113, 126], "text": "MissUniverse"}], "user_location": "antipolo city", "user_mentions": [{"indices": [3, 19], "screen_name": "TheJakolDiaries", "id": 4675012214, "name": "THE JAKOL DIARIES", "id_str": "4675012214"}], "followers": 8, "timestamp": "1485423332665", "following": 123, "in_reply_to_screen_name": null, "screen_name": "jaztinechael"}
{"description": "I love me some non aggression principle. Gimme some of them there property rights too. Ya know, of the inalienable variety.", "text": "RT @beyonce4pres: Facebook only bans right wing fake news, and doesn't care about leftist fake news! Retweet to spread the word! https://t.\u2026", "hashtags": [], "user_location": "Canada", "user_mentions": [{"indices": [3, 16], "screen_name": "beyonce4pres", "id": 2425271976, "name": "Libertarian Memes", "id_str": "2425271976"}], "followers": 15, "timestamp": "1485423458661", "following": 90, "in_reply_to_screen_name": null, "screen_name": "McLiberty11"}
{"description": null, "text": "#Now2016 #NOWFifthHarmony #VideoMTV2016 Fifth Harmony Beyonc\u00e9 https://t.co/DAqGJAHWeo https://t.co/Zgsy70MWNF", "hashtags": [{"indices": [0, 8], "text": "Now2016"}, {"indices": [9, 25], "text": "NOWFifthHarmony"}, {"indices": [26, 39], "text": "VideoMTV2016"}], "user_location": null, "user_mentions": [], "followers": 0, "timestamp": "1485423767661", "following": 0, "in_reply_to_screen_name": null, "screen_name": "sapsvotando5h"}
{"description": "from @lmjcrown", "text": "#VideoMTV2016 Fifth Harmony e Beyonc\u00e9 #NOW2016 #NOWFifthHarmony https://t.co/OMliU4qtnb", "hashtags": [{"indices": [0, 13], "text": "VideoMTV2016"}, {"indices": [38, 46], "text": "NOW2016"}, {"indices": [47, 63], "text": "NOWFifthHarmony"}], "user_location": null, "user_mentions": [], "followers": 0, "timestamp": "1485424188659", "following": 1, "in_reply_to_screen_name": null, "screen_name": "DrunkForDinahJ"}
{"description": null, "text": "beyonce hot nude https://t.co/jbzO7Q4GKR", "hashtags": [], "user_location": null, "user_mentions": [], "followers": 0, "timestamp": "1485424453660", "following": 3, "in_reply_to_screen_name": null, "screen_name": "Y_JMdiet"}
{"description": "My own muse. Poe's cat. Cherry bomb. Jigsaw woman.", "text": "RT @Berlustinho: Por favor, mirad este tributo, es una bestialidad. \n\nBeyonc\u00e9, Ed Sheeran &amp; Gary Clark Jr. Tribute Stevie Wonder\u2026 ", "hashtags": [], "user_location": "Brasil-Espa\u00f1a", "user_mentions": [{"indices": [3, 15], "screen_name": "Berlustinho", "id": 1499289019, "name": "Ber", "id_str": "1499289019"}], "followers": 1061, "timestamp": "1485424682666", "following": 910, "in_reply_to_screen_name": null, "screen_name": "Lost0f_Sense"}
{"description": "stayed to see the sun rise.", "text": "RT @YasBeyonce: I JUST MET LANA DEL REY OMFG SHES SO BEATIFULLL I CANT BREATHE http://t.co/rQ2P9tsZtX", "hashtags": [], "user_location": "\u2708\ufe0f Philippines!", "user_mentions": [{"indices": [3, 14], "screen_name": "YasBeyonce", "id": 2724387790, "name": "emily xcx", "id_str": "2724387790"}], "followers": 1356, "timestamp": "1485424730661", "following": 1049, "in_reply_to_screen_name": null, "screen_name": "basteboi"}
